HiVis/Aggregation.py
HiVis/Aggregation_utils.py
HiVis/HiVis.py
HiVis/HiVis_analysis.py
HiVis/HiVis_plot.py
HiVis/HiVis_utils.py
HiVis/__init__.py
HiVis/other_utils.py
hivis-0.9.dist-info/licenses/LICENSE
hivis-0.9.dist-info/METADATA
hivis-0.9.dist-info/WHEEL
hivis-0.9.dist-info/top_level.txt
hivis-0.9.dist-info/RECORD
