Metadata-Version: 2.4
Name: HiVis
Version: 0.9
Summary: A user friendly tool for working with VisiumHD data
Home-page: https://github.com/roynov01/HiVis
Author: Roy Novoselsky
Author-email: Roy Novoselsky <roy.novoselsky@weizmann.ac.il>
License: The MIT License (MIT)
Project-URL: Home, https://github.com/roynov01/HiVis
Project-URL: Documentation, https://hivis.readthedocs.io/en/latest/
Classifier: Intended Audience :: Science/Research
Classifier: Topic :: Scientific/Engineering :: Bio-Informatics
Classifier: Programming Language :: Python :: 3
Classifier: Programming Language :: Python :: 3.10
Classifier: License :: OSI Approved :: MIT License
Classifier: Operating System :: OS Independent
Requires-Python: >=3.10
License-File: LICENSE
Requires-Dist: numpy>=2.1.3
Requires-Dist: scipy>=1.15.2
Requires-Dist: matplotlib>=3.10.1
Requires-Dist: pandas>=2.2.3
Requires-Dist: seaborn>=0.13.2
Requires-Dist: scanpy==1.11.0
Requires-Dist: anndata>=0.11.3
Requires-Dist: adjustText
Requires-Dist: pyarrow>=19.0.1
Requires-Dist: pillow>=11.1.0
Requires-Dist: tqdm>=4.67.1
Requires-Dist: shapely>=2.0.7
Requires-Dist: geopandas>=1.0.1
Requires-Dist: dill>=0.3.9
Requires-Dist: tifffile>=2025.3.13
Requires-Dist: statsmodels>=0.14.4
Requires-Dist: scikit-learn>=1.5.2
Dynamic: author
Dynamic: home-page
Dynamic: license-file
Dynamic: requires-python
Dynamic: summary
